<mugl>
  <window border="0" margin="0" padding="0"/>
  <legend visible="false"/>
  <plotarea marginbottom="50" marginleft="60" marginright="0" margintop="0" color="0xf6f6f1" border="2" bordercolor="0x666"/>

  <horizontalaxis id="x" linewidth="0" min="-0.02" max="1.73" type="number" tickmax="0" tickmin="-3" tickcolor="0x666" color="0x666">
    <labels>
      <label format="%4d" spacing="10 5"/>
      <label format="%2f" spacing="2 1 .75 .5 .25 .1"/>
    </labels>
    <title anchor="0 5" position="-10 -10">Trail Distance In Miles</title>
    <pan min="-5" max="7"></pan>
    <binding id="xbinding" min="-0.02" max="1.73"></binding>
  </horizontalaxis>

  <verticalaxis id="y" linewidth="0" min="0" max="7000" type="number" tickmax="0" tickmin="-3" tickcolor="0x666" color="0x666">
    <labels format="%4d" spacing="1000 500 100 50 25 10 5 1" densityfactor="0.7"></labels>
    <title anchor="0 -4" angle="90" position="-25 0">Elevation In Feet</title>
    <pan min="0" max="7000"></pan>
    <binding id="ybinding" min="0" max="7000"></binding>
  </verticalaxis>

  <plot>
    <legend visible="false"/>
    <horizontalaxis ref="x"><variable ref="distance"/></horizontalaxis>
    <verticalaxis ref="y"><variable ref="elevation"/></verticalaxis>
    <renderer type="fill">
	  <option name="linewidth" value="2"/>
      <option name="linecolor" value="0xdc143c"/>
      <option name="fillcolor" value="0xd8debd"/>
    </renderer>
    <datatips format="Distance: {0} miles%n Elevation: {1} feet" bgcolor="0xc3bcaa" bordercolor="0xc3bcaa"/>
  </plot>

  <plot>
    <legend visible="false"/>
    <horizontalaxis ref="x"><variable ref="distanceStartPoint"/></horizontalaxis>
    <verticalaxis ref="y"><variable ref="elevationStartPoint"/></verticalaxis>
    <renderer type="point">
      <option name="pointsize" value="6"/>
      <option name="pointcolor" value="0xdc143c"/>
      <option name="pointoutlinecolor" value="0xdc143c"/>
    </renderer>
  </plot>

  <data>
    <variables>
      <variable column="0" id="distanceStartPoint" type="number"/>
      <variable column="1" id="elevationStartPoint" type="number"/>
    </variables>
    <values>
0.000000000	1965.8112
    </values>
  </data>

  <data>
    <variables>
      <variable column="0" id="distance" type="number"/>
      <variable column="1" id="elevation" type="number"/>
    </variables>
    <values>		
	
0.000000000	1965.8112
0.002872008	1966.8372
0.004799039	1967.4989
0.00672607	1967.9019
0.009292325	1968.6624
0.011858612	1969.7057
0.014067775	1969.648
0.016276887	1969.3705
0.019524864	1970.0947
0.022657464	1968.2603
0.025089706	1967.6418
0.027521948	1966.6206
0.030753712	1964.4808
0.033908357	1962.0246
0.036168733	1960.0505
0.038429163	1958.3518
0.041714632	1956.4334
0.045000102	1954.5826
0.04828557	1952.6981
0.051571084	1951.2918
0.054856509	1949.9289
0.058142022	1948.0443
0.061638142	1947.6568
0.065134292	1948.9816
0.068441479	1949.1446
0.072223496	1949.1041
0.076004042	1948.7343
0.079784635	1948.9726
0.083565181	1948.3324
0.087345774	1947.5814
0.089317508	1947.8306
0.091289243	1947.762
0.09486996	1947.7192
0.098450631	1949.2571
0.102031349	1950.5039
0.105612019	1951.5761
0.109276479	1948.978
0.112940986	1945.8147
0.116605446	1943.9863
0.120269953	1943.0834
0.123934413	1941.7061
0.126316209	1940.568
0.128698053	1940.3108
0.131937902	1940.3823
0.135177752	1938.866
0.138634932	1938.748
0.142092118	1939.1909
0.145549361	1938.7672
0.149006546	1938.3542
0.151403956	1938.804
0.15380141	1939.7229
0.157445373	1940.5891
0.161089421	1940.7602
0.164733384	1940.6516
0.168364967	1941.6803
0.17199655	1943.3478
0.175520639	1944.4279
0.179044674	1946.0341
0.182268936	1945.7497
0.185493267	1946.1024
0.189031875	1946.668
0.192570482	1947.5911
0.196109114	1949.048
0.199647721	1950.902
0.203186386	1950.997
0.206724994	1950.47
0.210263626	1949.121
0.213802233	1947.758
0.217340841	1945.9935
0.220073318	1946.44
0.22235201	1945.1711
0.224630702	1943.8038
0.227263082	1944.7942
0.229895435	1945.4034
0.232918945	1945.7822
0.235914214	1946.6443
0.238909423	1947.0348
0.241904708	1947.6198
0.244899917	1947.7966
0.248065027	1947.1401
0.251096599	1945.522
0.253595027	1944.0682
0.256093462	1943.2745
0.25813918	1942.1539
0.26018494	1941.1023
0.263076616	1939.99
0.265155206	1940.0651
0.267065859	1940.2462
0.268976537	1940.7794
0.27244447	1941.0633
0.27591249	1941.7711
0.278077034	1941.0359
0.280241563	1940.1712
0.283434834	1941.489
0.286628044	1941.6723
0.289821327	1941.6472
0.293014598	1940.6013
0.295565154	1940.4858
0.298115715	1940.5241
0.301213255	1941.6441
0.304310795	1942.7641
0.308050085	1943.6816
0.311789415	1944.6442
0.315528752	1945.2588
0.319268082	1945.0743
0.323007371	1944.8437
0.325356693	1945.7745
0.327706014	1946.7052
0.329869674	1946.0389
0.332033388	1945.2532
0.334585924	1944.3662
0.33713846	1944.1512
0.340546361	1945.2498
0.343954253	1945.3515
0.347450905	1945.8412
0.351119349	1945.8732
0.353306277	1946.3326
0.355493149	1946.6107
0.357415224	1946.4423
0.359337248	1946.0919
0.36176653	1944.6464
0.364195761	1943.6136
0.366512818	1942.6297
0.369146073	1942.7199
0.371779297	1942.81
0.375336773	1941.82
0.378894248	1940.5906
0.382108447	1941.2378
0.385322587	1941.8177
0.388536786	1941.502
0.391473766	1941.5535
0.394937005	1940.1713
0.398400245	1938.8173
0.401863484	1938.3416
0.405523276	1937.797
0.409183014	1937.8348
0.412842805	1938.3352
0.416502544	1938.1223
0.419090846	1938.1842
0.421679148	1938.0806
0.423240563	1938.4606
0.425756569	1939.3048
0.428272575	1940.1185
0.430732152	1940.4449
0.433191781	1940.7713
0.436445002	1941.582
0.439698195	1942.5863
0.442443147	1942.152
0.445188014	1942.0741
0.447932967	1942.0928
0.450464391	1941.7562
0.452995892	1941.5308
0.455527316	1941.8719
0.458937342	1942.5657
0.462574145	1941.5565
0.466210901	1941.0579
0.469847704	1940.1521
0.473484419	1939.9323
0.477121222	1939.4663
0.480757979	1938.2465
0.484394781	1937.519
0.484696386	1937.3944
0.487345202	1935.8595
0.489993965	1934.8307
0.49264278	1934.8602
0.494937621	1934.3714
0.498429517	1934.1038
0.501921413	1933.7014
0.504841425	1934.1853
0.507761359	1934.8775
0.510681371	1935.2877
0.51326687	1935.9839
0.51585243	1936.9361
0.518437929	1937.9705
0.52196782	1939.0922
0.525497719	1939.0826
0.52902761	1938.9324
0.532557501	1939.4131
0.535911908	1937.5443
0.539266376	1935.0226
0.542620782	1933.8066
0.54597525	1933.4762
0.549329657	1933.5275
0.552684125	1933.2905
0.554787317	1933.5688
0.556890597	1933.9613
0.559107431	1934.0006
0.561324263	1934.2785
0.565034333	1935.2508
0.568365739	1934.8316
0.571697145	1934.3172
0.574434805	1934.0482
0.577172479	1933.9256
0.579435134	1933.7163
0.582364219	1933.824
0.585293303	1934.5695
0.588836509	1934.6766
0.591422731	1933.6272
0.594008953	1932.4044
0.59699964	1931.8509
0.598968163	1930.4939
0.600936686	1929.0609
0.60388673	1928.4386
0.607476049	1930.1111
0.611065364	1930.9259
0.614654684	1932.112
0.617914135	1933.4713
0.621173625	1934.8307
0.624433028	1935.7385
0.627692517	1936.1841
0.630951969	1936.3173
0.634211459	1936.9262
0.636880303	1936.8539
0.639549116	1935.8161
0.642217961	1934.5913
0.645940618	1934.2358
0.649663302	1934.6424
0.653385959	1933.8824
0.656505615	1933.8793
0.659625271	1933.0836
0.663152232	1933.5402
0.666679153	1933.9714
0.670051629	1934.0237
0.673424162	1933.6936
0.676796638	1934.2225
0.680169171	1934.528
0.683541646	1934.7023
0.686914179	1935.3336
0.690286655	1936.0117
0.693823695	1935.5143
0.697360781	1935.9984
0.700897821	1936.3862
0.70443486	1936.212
0.707971947	1936.1065
0.711508986	1936.1447
0.714066259	1936.023
0.716623559	1936.1917
0.719180832	1936.188
0.722651845	1935.0735
0.726122854	1934.7185
0.729593866	1934.1
0.733064921	1933.612
0.735459634	1933.9451
0.737854434	1933.6509
0.741055635	1934.5432
0.744293157	1935.3818
0.74753074	1936.1931
0.750768251	1936.9633
0.754005773	1937.1644
0.756142877	1937.2358
0.75827998	1937.2648
0.76040072	1937.3603
0.762521448	1937.3862
0.76617248	1937.1443
0.769909665	1936.6665
0.773646911	1936.5635
0.777384095	1936.8955
0.780708317	1936.8051
0.78403258	1936.8909
0.787356848	1937.4685
0.79068107	1938.3917
0.793933469	1936.8531
0.79734559	1936.2336
0.80052661	1935.4633
0.803707692	1935.3882
0.806829576	1935.3419
0.808975393	1935.1588
0.81112121	1934.989
0.814783374	1935.7772
0.817155244	1936.3034
0.819527155	1937.2818
0.822659903	1938.4343
0.824594402	1939.0105
0.8265289	1939.4346
0.83010567	1940.3902
0.832004209	1941.2166
0.833902805	1941.9212
0.835838956	1942.5975
0.837775195	1943.0355
0.840310603	1944.0101
0.842845954	1944.514
0.845415107	1944.8228
0.847984288	1945.4813
0.850553442	1946.3593
0.852750436	1946.4537
0.85494743	1946.3932
0.858203855	1946.5725
0.860283096	1947.0489
0.862362356	1947.763
0.863346678	1948.2295
0.865084546	1948.7605
0.86595061	1949.0251
0.868621975	1949.7073
0.871293398	1950.168
0.873338027	1950.7568
0.875382657	1951.3456
0.878519086	1951.0983
0.881655524	1950.197
0.884178065	1949.5411
0.886700612	1948.9594
0.890055894	1947.5524
0.89341125	1946.1394
0.8970151	1945.0229
0.899043306	1945.0045
0.901071559	1945.3418
0.903141476	1945.898
0.905211417	1946.1958
0.908250586	1946.612
0.911289755	1947.5365
0.915050589	1948.1811
0.918675573	1947.6488
0.922300557	1947.311
0.925990638	1945.1661
0.929680749	1943.352
0.933370885	1941.7051
0.937060996	1940.5838
0.940751077	1938.9834
0.944172384	1938.384
0.947273004	1937.2946
0.949381286	1937.5871
0.951489629	1937.8797
0.955149686	1938.7201
0.958809743	1939.5258
0.962469804	1939.402
0.966129861	1938.4488
0.969789918	1937.3039
0.973044294	1938.0577
0.975188907	1937.6985
0.977333582	1937.4505
0.980278879	1938.3696
0.983224176	1939.2684
0.986169473	1939.136
0.98911477	1938.4729
0.992715782	1938.3264
0.99622752	1938.9127
0.998769001	1939.9327
1.001310544	1940.678
1.003852025	1941.4233
1.005938673	1942.4739
1.008025302	1943.5358
1.010643472	1944.6175
1.013261642	1945.9266
1.015195273	1945.6786
1.01712885	1945.3662
1.020316516	1944.5522
1.023812022	1942.8111
1.027307611	1942.6694
1.029485943	1942.5559
1.031664337	1942.5115
1.033821408	1941.6732
1.035978479	1941.496
1.039642885	1942.0039
1.043307289	1941.1813
1.045832981	1940.7045
1.04835864	1940.8223
1.050884332	1940.8336
1.053478416	1941.4129
1.056072413	1941.7451
1.058666497	1941.8592
1.061965576	1940.9092
1.065264596	1939.8993
1.068563675	1938.8895
1.07094281	1938.8094
1.073321966	1938.2883
1.076082901	1939.2931
1.078843849	1940.248
1.081604784	1941.2012
1.083957272	1941.6124
1.085664507	1941.7483
1.088888186	1942.0793
1.092111817	1942.2449
1.095189306	1942.4838
1.098266792	1942.6853
1.101344281	1943.0899
1.105115839	1943.0161
1.108887473	1943.1351
1.112659031	1941.7161
1.115387426	1941.5134
1.11811582	1940.9794
1.120844215	1939.2524
1.123886421	1940.9584
1.126928566	1942.1446
1.129970765	1943.3309
1.13301291	1944.3671
1.135785152	1945.2866
1.138557388	1945.761
1.141989193	1946.8884
1.145420921	1948.0817
1.148852727	1948.6642
1.152284455	1948.429
1.155716261	1948.4554
1.159147989	1948.0153
1.162579794	1949.1335
1.166011523	1949.2094
1.169479421	1948.8264
1.17294726	1948.6488
1.176415158	1949.0403
1.179882997	1949.0066
1.183350895	1948.9559
1.186818776	1948.9053
1.190286614	1948.87
1.193754513	1950.1745
1.197222351	1950.4241
1.200690249	1950.6223
1.203842825	1950.3029
1.2069954	1949.3638
1.210147958	1948.7838
1.213300533	1947.7066
1.215415184	1947.5639
1.217529834	1947.4872
1.220728513	1948.9045
1.223927136	1949.5535
1.227125815	1949.7673
1.230324439	1949.8551
1.233523117	1949.7854
1.236721741	1950.2281
1.240095863	1951.6015
1.243469926	1952.9899
1.246844031	1954.7513
1.250218153	1956.0413
1.253592216	1957.27
1.256966338	1958.248
1.259575612	1955.8413
1.262184943	1953.4449
1.264794217	1951.024
1.268093553	1950.4166
1.271392898	1949.1452
1.274692234	1947.7594
1.277991578	1946.4452
1.281290915	1944.4539
1.284590259	1941.5335
1.287314312	1941.1766
1.290038367	1940.6073
1.293467273	1943.2179
1.296896243	1944.3743
1.30032515	1945.2453
1.303754056	1946.2999
1.307182962	1947.1829
1.310611932	1947.6017
1.314040839	1948.1389
1.316994096	1948.0526
1.319649853	1946.7353
1.322305695	1945.7808
1.324961452	1945.404
1.328213891	1944.8212
1.331466331	1944.2258
1.335148149	1943.9422
1.338829923	1943.4292
1.342511741	1942.5178
1.346234914	1944.4064
1.34995803	1945.6804
1.353681203	1947.7131
1.357404319	1948.7617
1.361127492	1950.4904
1.364850608	1952.3772
1.368573782	1954.8483
1.371596019	1954.6048
1.374618257	1954.1451
1.377699467	1952.1258
1.380780726	1951.0592
1.383861974	1949.5707
1.386943184	1948.5647
1.390425527	1947.206
1.393907838	1946.3236
1.397390127	1945.6971
1.40087247	1945.0065
1.40423057	1945.0576
1.407588617	1945.3199
1.410946717	1945.4849
1.414304764	1946.675
1.417662864	1947
1.419960923	1947.1495
1.422258982	1947.2051
1.425395227	1947.1169
1.428531428	1946.5393
1.431667674	1946.5868
1.432447897	1946.719
1.435936481	1946.957
1.439425011	1947.3995
1.442913595	1948.0735
1.446402126	1948.4851
1.44989071	1948.7543
1.452763251	1950.7853
1.455635748	1952.102
1.458508288	1953.5554
1.461969687	1954.0847
1.465431055	1955.34
1.468892507	1956.1561
1.472353905	1956.8127
1.475815273	1957.7361
1.479276671	1959.7884
1.48118153	1960.4862
1.483086302	1961.184
1.485209534	1961.7891
1.487332717	1962.3777
1.489293966	1961.6165
1.491255154	1961.9221
1.493569654	1961.0546
1.495884155	1959.5318
1.498255887	1958.3013
1.500627559	1957.1967
1.503760284	1955.2875
1.506893008	1953.4015
1.509367799	1953.2726
1.511842574	1952.5906
1.514521794	1951.4504
1.517201014	1950.3422
1.52052663	1950.9112
1.523852294	1950.6168
1.52717791	1950.2136
1.529158446	1949.4317
1.531138982	1948.6497
1.533480343	1947.5376
1.535821674	1946.2012
1.538964396	1946.4736
1.542107158	1946.7528
1.545249928	1946.9235
1.548392689	1946.5397
1.551535411	1946.1311
1.55419027	1946.589
1.556155385	1945.7278
1.558120453	1944.8665
1.561647888	1944.0139
1.564904064	1944.3499
1.568160241	1943.9673
1.571416417	1943.0347
1.574633946	1942.5464
1.577851536	1942.3115
1.581069073	1941.9835
1.584286601	1941.8581
1.586993116	1941.4332
1.589699571	1940.7921
1.592406085	1940.1509
1.595392924	1940.6068
1.598379817	1941.4706
1.601366655	1942.4563
1.604353494	1943.0517
1.60803309	1944.4666
1.611712682	1945.6
1.615392279	1945.8669
1.618903105	1946.7148
1.622413907	1948.2124
1.625924734	1948.2598
1.628714328	1949.6373
1.631503962	1951.1789
1.634293556	1951.8748
1.637876199	1953.3655
1.641458793	1954.7664
1.645041435	1955.6073
1.646986066	1955.5243
1.64893078	1955.3514
1.652462321	1953.0626
1.655993912	1951.4226
1.658781193	1951.2057
1.66156851	1952.2402
1.664355791	1953.617
1.667654745	1952.2073
1.670953765	1951.4174
1.674252719	1949.8175
1.677548309	1948.2193
1.681254334	1945.6528
1.684960364	1943.6249
1.68866639	1942.5477
1.69237242	1942.9155
1.696078446	1943.5049
1.699784476	1943.7284
1.703490502	1944.5034
1.707020363	1944.4065
1.710714692	1945.0804
1.714408959	1945.4533
1.718103289	1945.6731
    </values>
  </data>
</mugl>
